lastmile/__init__.py
lastmile/_base_client.py
lastmile/_client.py
lastmile/_compat.py
lastmile/_constants.py
lastmile/_exceptions.py
lastmile/_files.py
lastmile/_models.py
lastmile/_qs.py
lastmile/_resource.py
lastmile/_response.py
lastmile/_streaming.py
lastmile/_types.py
lastmile/_version.py
lastmile/py.typed
lastmile/_utils/__init__.py
lastmile/_utils/_compat.py
lastmile/_utils/_datetime_parse.py
lastmile/_utils/_logs.py
lastmile/_utils/_proxy.py
lastmile/_utils/_reflection.py
lastmile/_utils/_resources_proxy.py
lastmile/_utils/_streams.py
lastmile/_utils/_sync.py
lastmile/_utils/_transform.py
lastmile/_utils/_typing.py
lastmile/_utils/_utils.py
lastmile/lib/.keep
lastmile/lib/__init__.py
lastmile/lib/auto_eval.py
lastmile/resources/__init__.py
lastmile/resources/datasets.py
lastmile/resources/evaluation.py
lastmile/resources/experiments.py
lastmile/resources/fine_tune_jobs.py
lastmile/resources/label_dataset_jobs.py
lastmile/resources/projects.py
lastmile/types/__init__.py
lastmile/types/dataset_copy_params.py
lastmile/types/dataset_copy_response.py
lastmile/types/dataset_create_params.py
lastmile/types/dataset_create_response.py
lastmile/types/dataset_delete_params.py
lastmile/types/dataset_delete_response.py
lastmile/types/dataset_finalize_file_upload_params.py
lastmile/types/dataset_finalize_file_upload_response.py
lastmile/types/dataset_get_download_url_params.py
lastmile/types/dataset_get_download_url_response.py
lastmile/types/dataset_get_params.py
lastmile/types/dataset_get_response.py
lastmile/types/dataset_get_view_params.py
lastmile/types/dataset_get_view_response.py
lastmile/types/dataset_list_params.py
lastmile/types/dataset_list_response.py
lastmile/types/dataset_upload_file_params.py
lastmile/types/dataset_upload_file_response.py
lastmile/types/evaluation_delete_run_params.py
lastmile/types/evaluation_delete_run_response.py
lastmile/types/evaluation_evaluate_dataset_params.py
lastmile/types/evaluation_evaluate_dataset_response.py
lastmile-0.23.2.dist-info/METADATA
lastmile-0.23.2.dist-info/WHEEL
lastmile-0.23.2.dist-info/licenses/LICENSE
lastmile-0.23.2.dist-info/RECORD
